flwave/__init__.py
flwave/flwaveapi.py
flwave-1.0.dist-info/LICENSE
flwave-1.0.dist-info/METADATA
flwave-1.0.dist-info/WHEEL
flwave-1.0.dist-info/top_level.txt
flwave-1.0.dist-info/RECORD
