Metadata-Version: 2.1
Name: flwave
Version: 1.0
Summary: A Python Package that enables easy integration of Flutterwave Payment Platform into a new or already existing python project
Author-email: Okechukwu Joshua Ifeanyi <joshoke111@gmail.com>
Maintainer-email: Okechukwu Joshua Ifeanyi <joshoke111@gmail.com>, Okamkpa Tobechukwu Gamaliel <tobechukwuokamkpa@gmail.com>
Project-URL: Flutterwave API official Docs, https://developer.flutterwave.com
Project-URL: Homepage, https://github.com/josh2297/flutterapi
Project-URL: Bug Tracker, https://github.com/josh2297/flutterapi/issues
Keywords: flutterwave,payment,django,flask,flutter
Classifier: Programming Language :: Python :: 3
Classifier: License :: OSI Approved :: MIT License
Classifier: Operating System :: OS Independent
Requires-Python: >=3.7
License-File: LICENSE
